dialog_workflow_local/Constants.py
dialog_workflow_local/DialogWorkflow.py
dialog_workflow_local/ProfileContext.py
dialog_workflow_local/__init__.py
dialog_workflow_local/action.py
dialog_workflow_local/utils.py
dialog_workflow_local-0.0.128.dist-info/METADATA
dialog_workflow_local-0.0.128.dist-info/WHEEL
dialog_workflow_local-0.0.128.dist-info/top_level.txt
dialog_workflow_local-0.0.128.dist-info/RECORD
